setup.py
aserna_probability/Binomialdistribution.py
aserna_probability/Gaussiandistribution.py
aserna_probability/Generaldistribution.py
aserna_probability/__init__.py
aserna_probability.egg-info/PKG-INFO
aserna_probability.egg-info/SOURCES.txt
aserna_probability.egg-info/dependency_links.txt
aserna_probability.egg-info/not-zip-safe
aserna_probability.egg-info/top_level.txt