Metadata-Version: 1.0
Name: aserna-probability
Version: 0.1
Summary: Gaussian and Binomial distributions
Home-page: UNKNOWN
Author: Santiago Serna
Author-email: UNKNOWN
License: UNKNOWN
Platform: UNKNOWN
